tmc_course/__init__.py
tmc_course/__main__.py
tmc_course/tmc_course.py
tmc_course/resources/__init__.py
tmc_course/resources/assignment_solution_en.template
tmc_course/resources/assignment_solution_fi.template
tmc_course/resources/assignment_test_en.template
tmc_course/resources/assignment_test_fi.template
tmc_course/resources/assignment_tmcproject_yml.template
tmc_course/resources/course_gitignore.template
tmc_course/resources/course_tmcproject_yml.template
tmc_course-1.0.0b6.dist-info/LICENSE
tmc_course-1.0.0b6.dist-info/METADATA
tmc_course-1.0.0b6.dist-info/WHEEL
tmc_course-1.0.0b6.dist-info/entry_points.txt
tmc_course-1.0.0b6.dist-info/top_level.txt
tmc_course-1.0.0b6.dist-info/RECORD
