Metadata-Version: 2.1
Name: tmc-course
Version: 1.0.0b6
Summary: TMC course and assignment creation helper
Author-email: Leo Leppänen <leo.leppanen@helsinki.fi>
License: Copyright (c) 2023 Leo Leppänen
Project-URL: repository, https://github.com/ljleppan/tmc-course
Keywords: TestMyCode,TMC,helper,teacher,tool
Classifier: Development Status :: 4 - Beta
Classifier: Environment :: Console
Classifier: License :: OSI Approved :: MIT License
Classifier: Programming Language :: Python :: 3
Classifier: Programming Language :: Python :: 3.9
Classifier: Programming Language :: Python :: 3.10
Classifier: Programming Language :: Python :: 3.11
Classifier: Programming Language :: Python :: 3 :: Only
Classifier: Programming Language :: Python :: Implementation :: CPython
Classifier: Typing :: Typed
Requires-Python: >=3.9
License-File: LICENSE
Requires-Dist: requests (>=2.28.2)
Requires-Dist: treelib (>=1.6.1)
Requires-Dist: tqdm (>=4.64.1)
Provides-Extra: dev
Requires-Dist: black (>=23.1.0) ; extra == 'dev'
Requires-Dist: build (>=0.10.0) ; extra == 'dev'
Requires-Dist: covdefaults (>=2.2.0) ; extra == 'dev'
Requires-Dist: coverage (>=7.1.0) ; extra == 'dev'
Requires-Dist: flake8 (>=6.0.0) ; extra == 'dev'
Requires-Dist: isort (>=5.12.0) ; extra == 'dev'
Requires-Dist: mypy (>=1.0.0) ; extra == 'dev'
Requires-Dist: pre-commit (>=3.0.0) ; extra == 'dev'
Requires-Dist: pytest (>=7.2.0) ; extra == 'dev'
Requires-Dist: responses (>=0.22.0) ; extra == 'dev'
Requires-Dist: tox (>=4.4.0) ; extra == 'dev'
Requires-Dist: types-requests (>=2.28.11.12) ; extra == 'dev'
Requires-Dist: types-setuptools (>=67.2.0.1) ; extra == 'dev'
Requires-Dist: types-tqdm (>=4.64.7.15) ; extra == 'dev'
Requires-Dist: twine (>=4.0.2) ; extra == 'dev'
Requires-Dist: wheel (>=0.38.4) ; extra == 'dev'
